LICENSE
netaudio/__init__.py
netaudio/__main__.py
netaudio/console/__init__.py
netaudio/console/application.py
netaudio/console/commands/__init__.py
netaudio/console/commands/channel/__init__.py
netaudio/console/commands/channel/_list.py
netaudio/console/commands/config/__init__.py
netaudio/console/commands/device/__init__.py
netaudio/console/commands/device/_list.py
netaudio/console/commands/subscription/__init__.py
netaudio/console/commands/subscription/_add.py
netaudio/console/commands/subscription/_list.py
netaudio/console/commands/subscription/_remove.py
netaudio/dante/__init__.py
netaudio/dante/browser.py
netaudio/dante/channel.py
netaudio/dante/const.py
netaudio/dante/control.py
netaudio/dante/device.py
netaudio/dante/multicast.py
netaudio/dante/subscription.py
netaudio/dante/subscription_status.py
netaudio/utils/__init__.py
netaudio/utils/timeout.py
netaudio-0.0.10.dist-info/entry_points.txt
netaudio-0.0.10.dist-info/LICENSE
netaudio-0.0.10.dist-info/WHEEL
netaudio-0.0.10.dist-info/METADATA
netaudio-0.0.10.dist-info/RECORD
