Metadata-Version: 2.1
Name: netaudio
Version: 0.0.10
Summary: List, configure, and control Dante network audio devices without Dante Controller
Home-page: https://github.com/chris-ritsen/network-audio-controller
License: Unlicense
Keywords: audinate,audio,cli,dante,network
Author: Christopher Ritsen
Author-email: chris.ritsen@gmail.com
Requires-Python: >=3.7,<4.0
Classifier: License :: Other/Proprietary License
Classifier: Programming Language :: Python :: 3
Classifier: Programming Language :: Python :: 3.10
Classifier: Programming Language :: Python :: 3.7
Classifier: Programming Language :: Python :: 3.8
Classifier: Programming Language :: Python :: 3.9
Classifier: Topic :: Multimedia :: Sound/Audio
Requires-Dist: cleo (>=0.8.1,<0.9.0)
Requires-Dist: netifaces (>=0.11.0,<0.12.0)
Requires-Dist: twisted (>=22.1.0,<23.0.0)
Requires-Dist: zeroconf (>=0.38.3,<0.39.0)
Project-URL: Documentation, https://github.com/chris-ritsen/network-audio-controller/wiki
Project-URL: Repository, https://github.com/chris-ritsen/network-audio-controller
